arkfunds/__init__.py
arkfunds/arkfunds.py
arkfunds/etf.py
arkfunds/stock.py
arkfunds/utils.py
arkfunds/yahoo.py
arkfunds-0.3.2.dist-info/LICENSE
arkfunds-0.3.2.dist-info/WHEEL
arkfunds-0.3.2.dist-info/METADATA
arkfunds-0.3.2.dist-info/RECORD
