Metadata-Version: 2.1
Name: arkfunds
Version: 0.3.2
Summary: Python library for monitoring Ark Invest funds data.
Home-page: https://github.com/frefrik/arkfunds-python
License: MIT
Keywords: ark,ark invest,ark funds,etf,funds,finance
Author: Fredrik Haarstad
Author-email: codemonkey@zomg.no
Requires-Python: >=3.7.1,<4.0
Classifier: License :: OSI Approved :: MIT License
Classifier: Programming Language :: Python :: 3
Classifier: Programming Language :: Python :: 3.8
Classifier: Programming Language :: Python :: 3.9
Provides-Extra: docs
Requires-Dist: Sphinx (>=4.1.2,<5.0.0); extra == "docs"
Requires-Dist: pandas (>=1.3.1,<2.0.0)
Requires-Dist: requests (>=2.26.0,<3.0.0)
Requires-Dist: sphinx-rtd-theme (>=0.5.2,<0.6.0); extra == "docs"
Project-URL: Repository, https://github.com/frefrik/arkfunds-python
